oxaigen/__init__.py
oxaigen/src/__init__.py
oxaigen/src/asset/__init__.py
oxaigen/src/asset/asset.py
oxaigen/src/asset_factory/__init__.py
oxaigen/src/asset_factory/notebook_asset.py
oxaigen/src/asset_factory/report_asset.py
oxaigen/src/authentication/__init__.py
oxaigen/src/authentication/authentication.py
oxaigen/src/config.py
oxaigen/src/constant.py
oxaigen/src/io_manager/__init__.py
oxaigen/src/io_manager/reports_io_manager.py
oxaigen/src/main.py
oxaigen/src/notebook/__init__.py
oxaigen/src/notebook/notebook_pdf_generator.py
oxaigen/src/notebook/s3_storage.py
oxaigen/src/orchestration/__init__.py
oxaigen/src/orchestration/resources/__init__.py
oxaigen/src/orchestration/resources/db_io_manager.py
oxaigen/src/orchestration/resources/dbt_translator.py
oxaigen/src/settings/__init__.py
oxaigen/src/settings/settings.py
oxaigen/src/storage/__init__.py
oxaigen/src/storage/azure_storage.py
oxaigen/src/storage/data_storage.py
oxaigen/src/util/__init__.py
oxaigen/src/util/api.py
oxaigen/src/util/exception.py
oxaigen/src/util/logging.py
oxaigen/src/util/token.py
oxaigen/src/util/util.py
oxaigen-0.0.2.6.dist-info/METADATA
oxaigen-0.0.2.6.dist-info/WHEEL
oxaigen-0.0.2.6.dist-info/RECORD
