Metadata-Version: 2.1
Name: oxaigen
Version: 0.0.2.6
Summary: Oxaigen Python SDK
Author: Luca Roggeveen
Author-email: luca@oxaigen.com
Requires-Python: >=3.10.12,<3.13
Classifier: Programming Language :: Python :: 3
Classifier: Programming Language :: Python :: 3.11
Requires-Dist: boto3 (>=1.35.23)
Requires-Dist: dagit (>=1.8.7)
Requires-Dist: dagster-airbyte (>=0.24.7)
Requires-Dist: dagster-aws (>=0.24.7)
Requires-Dist: dagster-azure (>=0.24.7)
Requires-Dist: dagster-dbt (>=0.24.7)
Requires-Dist: dagster-mlflow (>=0.24.7)
Requires-Dist: dagster-postgres (>=0.24.7)
Requires-Dist: dagstermill (>=0.26.14)
Requires-Dist: dbt-postgres (>=1.8.2)
Requires-Dist: mlflow (>=2.16.2)
Requires-Dist: numpy (>=1.26.4,<2.0.0)
Requires-Dist: pandas (>=2.1.0,<3.0.0)
Requires-Dist: psycopg2-binary (>=2.9.9,<3.0.0)
Requires-Dist: pydantic
Requires-Dist: scikit-learn (>=1.4.0,<2.0.0)
